LICENSE.txt
MANIFEST.in
README.rst
__init__.py
serializer.py
setup.cfg
setup.py
setup_develop_mode.py
util.py
./LICENSE.txt
./README.rst
./__init__.py
./serializer.py
./setup_develop_mode.py
./util.py
./client/__init__.py
./client/ajax.py
./client/auth.py
./client/lang_chooser.py
./client/tree (copier 1).py
./client/tree.py
./client/websocket.py
./server/__init__.py
./server/ajax.py
./server/base_backend.py
./server/base_rpc.py
./server/compile_brython.py
./server/flask_backend.py
./server/fullpy.owl
./server/gunicorn_backend.py
./server/gunicorn_multiprocess.py
./server/lock.py
./server/websocket.py
./server/werkzeug_backend.py
./static/fullpy.css
client/__init__.py
client/ajax.py
client/auth.py
client/lang_chooser.py
client/tree (copier 1).py
client/tree.py
client/websocket.py
demo/demo_1_hello_world_ajax/client.py
demo/demo_1_hello_world_ajax/server.py
demo/demo_2_hello_world_websocket/client.py
demo/demo_2_hello_world_websocket/server.py
demo/demo_3_translation/client.py
demo/demo_3_translation/server.py
demo/demo_3_translation/translation.py
demo/demo_4_chat_websocket/client.py
demo/demo_4_chat_websocket/server.py
demo/demo_5_multiroom_chat_websocket/client.py
demo/demo_5_multiroom_chat_websocket/server.py
demo/demo_6_multiroom_chat_with_serialization_websocket/client.py
demo/demo_6_multiroom_chat_with_serialization_websocket/server.py
demo/static/brython.js
demo/static/brython_stdlib.js
demo/static/demo_4.css
demo/static/fullpy.css
doc/backends.rst
doc/client.rst
doc/conf.py
doc/contact.rst
doc/demos.rst
doc/group.rst
doc/html.rst
doc/index.rst
doc/install.rst
doc/onto.rst
doc/rpc.rst
doc/serializer.rst
doc/server.rst
doc/session.rst
doc/start.rst
doc/translations.rst
doc/_images/chat.png
doc/doctrees/backends.doctree
doc/doctrees/client.doctree
doc/doctrees/contact.doctree
doc/doctrees/demos.doctree
doc/doctrees/environment.pickle
doc/doctrees/group.doctree
doc/doctrees/html.doctree
doc/doctrees/index.doctree
doc/doctrees/install.doctree
fullpy.egg-info/PKG-INFO
fullpy.egg-info/SOURCES.txt
fullpy.egg-info/dependency_links.txt
fullpy.egg-info/requires.txt
fullpy.egg-info/top_level.txt
