Metadata-Version: 2.1
Name: fullpy
Version: 0.2
Summary: A module for developping client-server web application entirely in Python, with semantic data persistance using OWL ontologies and remote function calls (RPC) via Ajax or WebSocket.
Home-page: https://bitbucket.org/jibalamy/fullpy
Author: Lamy Jean-Baptiste (Jiba)
Author-email: jibalamy@free.fr
License: LGPLv3+
Classifier: Development Status :: 3 - Alpha
Classifier: Intended Audience :: Developers
Classifier: Intended Audience :: Information Technology
Classifier: Intended Audience :: Science/Research
Classifier: License :: OSI Approved :: GNU Lesser General Public License v3 or later (LGPLv3+)
Classifier: Operating System :: OS Independent
Classifier: Programming Language :: Python :: 3
Classifier: Programming Language :: Python :: 3 :: Only
Classifier: Topic :: Software Development :: Libraries :: Python Modules
Classifier: Topic :: Internet :: WWW/HTTP :: Dynamic Content
Classifier: Topic :: Internet :: WWW/HTTP :: WSGI :: Application
Requires-Python: >=3.6
License-File: LICENSE.txt
Requires-Dist: brython
Requires-Dist: owlready2
Requires-Dist: gunicorn
Requires-Dist: gevent
Requires-Dist: flask
